parole/__init__.py
parole/generator.py
parole-0.1.1.dist-info/LICENSE
parole-0.1.1.dist-info/METADATA
parole-0.1.1.dist-info/WHEEL
parole-0.1.1.dist-info/entry_points.txt
parole-0.1.1.dist-info/top_level.txt
parole-0.1.1.dist-info/RECORD
