Metadata-Version: 2.1
Name: parole
Version: 0.1.1
Summary: A simple password generator
Home-page: https://github.com/merschformann/parole
Author: Marius Merschformann
Author-email: marius.merschformann@gmail.com
License: UNKNOWN
Platform: UNKNOWN
Classifier: Programming Language :: Python :: 3
Classifier: License :: OSI Approved :: MIT License
Classifier: Operating System :: OS Independent
Classifier: Environment :: Console
Requires-Dist: pyperclip (>=1.8.1)
